pylagg/cgr.py
pylagg/config.py
pylagg/cutadapt.py
pylagg/ena.py
pylagg/jellyfish.py
pylagg/main.py
pylagg-0.5.1.dist-info/LICENSE
pylagg-0.5.1.dist-info/METADATA
pylagg-0.5.1.dist-info/WHEEL
pylagg-0.5.1.dist-info/entry_points.txt
pylagg-0.5.1.dist-info/RECORD
